dbt/adapters/athena_community/__init__.py
dbt_athena_community-1.10.0.dist-info/METADATA
dbt_athena_community-1.10.0.dist-info/WHEEL
dbt_athena_community-1.10.0.dist-info/licenses/LICENSE
dbt_athena_community-1.10.0.dist-info/RECORD
