Metadata-Version: 2.4
Name: dbt-athena-community
Version: 1.10.0
Summary: The athena adapter plugin for dbt (data build tool)
Project-URL: Homepage, https://github.com/dbt-labs/dbt-adapters/tree/main/dbt-athena
Project-URL: Documentation, https://docs.getdbt.com
Project-URL: Repository, https://github.com/dbt-labs/dbt-adapters.git#subdirectory=dbt-athena
Project-URL: Issues, https://github.com/dbt-labs/dbt-adapters/issues
Project-URL: Changelog, https://github.com/dbt-labs/dbt-adapters/blob/main/dbt-athena/CHANGELOG.md
Author-email: dbt Labs <info@dbtlabs.com>
Maintainer-email: dbt Labs <info@dbtlabs.com>
License-File: LICENSE
Keywords: adapter,adapters,athena,database,dbt,dbt Cloud,dbt Core,dbt Labs,dbt-core,elt
Classifier: Development Status :: 5 - Production/Stable
Classifier: License :: OSI Approved :: Apache Software License
Classifier: Operating System :: MacOS :: MacOS X
Classifier: Operating System :: Microsoft :: Windows
Classifier: Operating System :: POSIX :: Linux
Classifier: Programming Language :: Python :: 3.10
Classifier: Programming Language :: Python :: 3.11
Classifier: Programming Language :: Python :: 3.12
Requires-Python: >=3.10.0
Requires-Dist: dbt-athena==1.10.0
